{
	"name": "BlobCreatedEvent",
	"properties": {
		"annotations": [],
		"runtimeState": "Started",
		"pipelines": [
			{
				"pipelineReference": {
					"referenceName": "EventDrivenPipeLine",
					"type": "PipelineReference"
				}
			}
		],
		"type": "BlobEventsTrigger",
		"typeProperties": {
			"blobPathBeginsWith": "/mydata/blobs/",
			"blobPathEndsWith": ".csv",
			"ignoreEmptyBlobs": true,
			"scope": "/subscriptions/3913cf8a-9dd5-439b-a762-9f021887fa27/resourceGroups/Cog_Practice/providers/Microsoft.Storage/storageAccounts/dineshadfacc2",
			"events": [
				"Microsoft.Storage.BlobCreated"
			]
		}
	}
}